monumenten/__init__.py
monumenten/_processing.py
monumenten/_version.py
monumenten/client.py
monumenten/logging.py
monumenten/py.typed
monumenten/_api/__init__.py
monumenten/_api/_cultureel_erfgoed.py
monumenten/_api/_kadaster.py
monumenten-1.0.0.dist-info/licenses/LICENSE
monumenten-1.0.0.dist-info/METADATA
monumenten-1.0.0.dist-info/WHEEL
monumenten-1.0.0.dist-info/top_level.txt
monumenten-1.0.0.dist-info/RECORD
