Metadata-Version: 2.4
Name: monumenten
Version: 1.0.0
Summary: Checkt op basis van BAG verblijfsobject-ids of het verblijfsobject een monument en/of rijksbeschermd stadsgezicht is.
Author-email: Woonstad Rotterdam <info@woonstadrotterdam.nl>, Ben Verhees <ben.verhees@woonstadrotterdam.nl>, Tomer Gabay <tomer.gabay@woonstadrotterdam.nl>
License: MIT License
Project-URL: Homepage, https://github.com/woonstadrotterdam/monumenten
Project-URL: Issues, https://github.com/woonstadrotterdam/monumenten/issues
Keywords: monument,bag,stadsgezicht,monumentenregister,beschermd
Classifier: Programming Language :: Python :: 3.9
Classifier: Programming Language :: Python :: 3.10
Classifier: Programming Language :: Python :: 3.11
Classifier: Programming Language :: Python :: 3.12
Classifier: License :: OSI Approved :: MIT License
Classifier: Operating System :: OS Independent
Requires-Python: >=3.9.5
License-File: LICENSE
Requires-Dist: aiocache>=0.12.3
Requires-Dist: aiohttp>=3.10.10
Requires-Dist: tqdm>=4.66.5
Requires-Dist: pandas>=2.0.0
Requires-Dist: geopandas>=1.0.1
Provides-Extra: test
Requires-Dist: pre-commit==3.*; extra == "test"
Requires-Dist: pytest==8.*; extra == "test"
Requires-Dist: pytest-cov==5.*; extra == "test"
Requires-Dist: pytest-asyncio==0.24.*; extra == "test"
Provides-Extra: dev
Requires-Dist: monumenten[test]; extra == "dev"
Requires-Dist: ruff==0.9.5; extra == "dev"
Requires-Dist: pandas-stubs>=2.0.0; extra == "dev"
Dynamic: license-file
